<skin>
  <!-- NumberZapPicon_large-->
	<screen name="NumberZapPicon" position="center,center" size="905,365" title="QuickZap" backgroundColor="transparent" flags="wfNoBorder">
	
		<eLabel name="picon" position="455,0" size="448,272" zPosition="-20" backgroundColor="line"  />
		<eLabel name="BG_Picon" position="458,3" size="442,266" zPosition="-10" backgroundColor="background"  />
		<widget source="Service" render="Picon" position="459,4" size="440,264" zPosition="1" transparent="1" alphatest="blend">
			<convert type="ServiceName">Reference</convert>
		</widget>
      
		<eLabel name="number" position="0,0" size="448,272" zPosition="-20" backgroundColor="line"  /> 
		<eLabel name="BG_Number" position="3,3" size="442,266" zPosition="-10" backgroundColor="background"  />
		<widget name="number" position="4,4" size="440,264" halign="center" valign="center" font="Regular; 160" foregroundColor="white" backgroundColor="background" zPosition="10" transparent="1" />
	  
		<eLabel name="name" position="0,280" size="903,83" zPosition="-20" backgroundColor="grey" /> 
		<eLabel name="BG_Name" position="2,282" size="899,79" zPosition="-10" backgroundColor="bluelabeltranzp"  />
		<widget name="servicename" position="5,285" size="895,75" halign="center" valign="center" font="Regular;60" foregroundColor="white" backgroundColor="bluelabeltranzp" noWrap="1" transparent="1" zPosition="2" />
  
	</screen>
    </skin>
